{
  "fileName": "Farah_Warnakulasuriya_SE_CV ",
  "parsers": {
    "default": {
      "name": true,
      "email": true,
      "phone": true,
      "linkedin": false,
      "github": false,
      "location": false,
      "experienceCount": 7,
      "educationCount": 2,
      "skillsCount": 35,
      "projectsCount": 0,
      "honorsCount": 0,
      "languagesCount": 0,
      "certificationsCount": 0,
      "coveragePercentage": 100,
      "missingContentCount": 0
    },
    "serter": {
      "name": true,
      "email": true,
      "phone": true,
      "linkedin": false,
      "github": false,
      "location": true,
      "experienceCount": 14,
      "educationCount": 4,
      "skillsCount": 7,
      "projectsCount": 5,
      "honorsCount": 0,
      "languagesCount": 0,
      "certificationsCount": 0,
      "coveragePercentage": 50,
      "missingContentCount": 1
    },
    "student": {
      "name": true,
      "email": true,
      "phone": true,
      "linkedin": false,
      "github": false,
      "location": true,
      "experienceCount": 2,
      "educationCount": 2,
      "skillsCount": 0,
      "projectsCount": 2,
      "honorsCount": 0,
      "languagesCount": 0,
      "certificationsCount": 0,
      "coveragePercentage": 0,
      "missingContentCount": 2
    }
  },
  "fileSize": 98,
  "timestamp": "2025-03-26T12:56:33.291Z",
  "bestParser": "default"
}